{
	"miniprogramRoot": "miniprogram/",
	"pluginRoot": "plugin/",
	"compileType": "plugin",
	"setting": {
		"urlCheck": false,
		"es6": true,
		"enhance": false,
		"postcss": true,
		"preloadBackgroundData": false,
		"minified": true,
		"newFeature": false,
		"coverView": true,
		"nodeModules": true,
		"autoAudits": false,
		"showShadowRootInWxmlPanel": true,
		"scopeDataCheck": false,
		"uglifyFileName": false,
		"checkInvalidKey": true,
		"checkSiteMap": true,
		"uploadWithSourceMap": true,
		"compileHotReLoad": false,
		"babelSetting": {
			"ignore": [],
			"disablePlugins": [],
			"outputPath": ""
		},
		"useIsolateContext": true,
		"useCompilerModule": true,
		"userConfirmedUseCompilerModuleSwitch": false
	},
	"appid": "wx9da882c106b9ab9f",
	"projectname": "wx-canvas-2d",
	"simulatorType": "wechat",
	"simulatorPluginLibVersion": {},
	"condition": {}
}